{
    "@context": {
        "schema": "http://schema.org/"
    },
    "@id": "https://nfdi4culture.de/id/E4255",
    "schema:MusicComposition": {
        "@id": "https://performance.musiconn.de/work/sonaten-klavier-op-31-nr-3-beethoven-ludwig-van",
        "schema:name": "Sonaten, Klavier, op. 31. Nr. 3 (Beethoven, Ludwig van)",
        "schema:composer": [
            {
                "@type": "schema:Person",
                "@id": {
                    "https://performance.musiconn.de/person/beethoven-ludwig-van-1770-1827": {
                        "gnd": "https://d-nb.info/gnd/118508288",
                        "viaf": "https://viaf.org/viaf/32182557"
                    }
                }
            }
        ],
        "schema:description": [],
        "schema:alternateName": [
            {
                "@value": "Sonaten, Klavier, op. 31. Nr. 3"
            },
            {
                "@value": "La chasse"
            },
            {
                "@value": "Jagdsonate"
            },
            {
                "@value": "Sonaten, Kl op. 31, 3"
            },
            {
                "@value": "Sonaten, Kl op. 31,3"
            }
        ],
        "schema:genre": [
            {
                "@id": {
                    "https://performance.musiconn.de/subject/sonate": {
                        "gnd": "https://d-nb.info/gnd/4131190-5",
                        "viaf": null
                    }
                }
            }
        ],
        "schema:includedComposition": [
            {
                "@type": "schema:MusicComposition",
                "@id": {
                    "https://performance.musiconn.de/work/sonaten-klavier-op-31-nr-3-presto-con-fuoco-beethoven-ludwig-van": {
                        "gnd": "https://d-nb.info/gnd/1079137491",
                        "viaf": "https://viaf.org/viaf/69144898755550290246"
                    }
                }
            }
        ],
        "schema:subjectOf": [],
        "schema:contributor": [
            {
                "@type": "schema:Person",
                "@id": {
                    "https://performance.musiconn.de/person/albert-eugen-d-1864-1932": {
                        "gnd": "https://d-nb.info/gnd/118501437",
                        "viaf": "https://viaf.org/viaf/34642370"
                    }
                }
            }
        ]
    }
}