{
    "@context": {
        "schema": "http://schema.org/"
    },
    "@id": "https://nfdi4culture.de/id/E4255",
    "schema:MusicComposition": {
        "@id": "https://performance.musiconn.de/work/sonaten-klavier-op-57-f-moll-beethoven-ludwig-van",
        "schema:name": "Sonaten, Klavier, op. 57 (f-Moll) (Beethoven, Ludwig van)",
        "schema:composer": [
            {
                "@type": "schema:Person",
                "@id": {
                    "https://performance.musiconn.de/person/beethoven-ludwig-van-1770-1827": {
                        "gnd": "https://d-nb.info/gnd/118508288",
                        "viaf": "https://viaf.org/viaf/32182557"
                    }
                }
            }
        ],
        "schema:description": [
            {
                "@value": "Nummerierung im Werkverzeichnis nicht genannt"
            }
        ],
        "schema:alternateName": [
            {
                "@value": "Sonaten, Klavier, op. 57 (f-Moll)"
            },
            {
                "@value": "Sonaten, Kl, op. 57"
            },
            {
                "@value": "Appassionata"
            },
            {
                "@value": "Sonata Apassionata"
            },
            {
                "@value": "Appassionata sonata"
            },
            {
                "@value": "Sonaten, Kl op. 57"
            }
        ],
        "schema:genre": [
            {
                "@id": {
                    "https://performance.musiconn.de/subject/sonate": {
                        "gnd": "https://d-nb.info/gnd/4131190-5",
                        "viaf": null
                    }
                }
            }
        ],
        "schema:includedComposition": [
            {
                "@type": "schema:MusicComposition",
                "@id": {
                    "https://performance.musiconn.de/work/sonaten-klavier-op-57-f-moll-andante-con-moto-beethoven-ludwig-van": {
                        "gnd": "https://d-nb.info/gnd/300606494",
                        "viaf": "https://viaf.org/viaf/202951692"
                    }
                }
            }
        ],
        "schema:subjectOf": [
            {
                "@type": "schema:event",
                "@id": {
                    "https://performance.musiconn.de/event/5-kammermusik-abend-kleiner-konzertsaal-frankfurt-a-m-1872-12-30-19-00": {
                        "gnd": null,
                        "viaf": null
                    }
                }
            }
        ],
        "schema:contributor": [
            {
                "@type": "schema:Person",
                "@id": {
                    "https://performance.musiconn.de/person/badura-skoda-paul-1927": {
                        "gnd": "https://d-nb.info/gnd/124411266",
                        "viaf": "https://viaf.org/viaf/56605340"
                    }
                }
            },
            {
                "@type": "schema:Person",
                "@id": {
                    "https://performance.musiconn.de/person/buths-julius-1851-1920": {
                        "gnd": "https://d-nb.info/gnd/117184195",
                        "viaf": "https://viaf.org/viaf/94024708"
                    }
                }
            },
            {
                "@type": "schema:Person",
                "@id": {
                    "https://performance.musiconn.de/person/gieseking-walter-1895-1956": {
                        "gnd": "https://d-nb.info/gnd/118694820",
                        "viaf": "https://viaf.org/viaf/51875300"
                    }
                }
            },
            {
                "@type": "schema:Person",
                "@id": {
                    "https://performance.musiconn.de/person/gilels-emil-grigorevic-1916-1985": {
                        "gnd": "https://d-nb.info/gnd/119056445",
                        "viaf": "https://viaf.org/viaf/44485204"
                    }
                }
            },
            {
                "@type": "schema:Person",
                "@id": {
                    "https://performance.musiconn.de/person/hirschfeldt-rosalie-1830": {
                        "gnd": "https://d-nb.info/gnd/1257458981",
                        "viaf": null
                    }
                }
            },
            {
                "@type": "schema:Person",
                "@id": {
                    "https://performance.musiconn.de/person/korobejnikov-andrej-1986": {
                        "gnd": "https://d-nb.info/gnd/13429114X",
                        "viaf": "https://viaf.org/viaf/6147316"
                    }
                }
            },
            {
                "@type": "schema:Person",
                "@id": {
                    "https://performance.musiconn.de/person/leipholz-wilhelm-leopold-1843": {
                        "gnd": "https://d-nb.info/gnd/1262247616",
                        "viaf": "https://viaf.org/viaf/7924165814874559860007"
                    }
                }
            },
            {
                "@type": "schema:Person",
                "@id": {
                    "https://performance.musiconn.de/person/ney-elly-1882-1968": {
                        "gnd": "https://d-nb.info/gnd/118587552",
                        "viaf": "https://viaf.org/viaf/12494112"
                    }
                }
            },
            {
                "@type": "schema:Person",
                "@id": {
                    "https://performance.musiconn.de/person/say-fazil-1970": {
                        "gnd": "https://d-nb.info/gnd/132551365",
                        "viaf": "https://viaf.org/viaf/42038387"
                    }
                }
            },
            {
                "@type": "schema:Person",
                "@id": {
                    "https://performance.musiconn.de/person/varga-csilla": {
                        "gnd": null,
                        "viaf": null
                    }
                }
            },
            {
                "@type": "schema:Person",
                "@id": {
                    "https://performance.musiconn.de/person/volkland-alfred-1841-1905": {
                        "gnd": "https://d-nb.info/gnd/117489719",
                        "viaf": "https://viaf.org/viaf/15547764"
                    }
                }
            }
        ]
    }
}