{
    "@context": {
        "schema": "http://schema.org/"
    },
    "@id": "https://nfdi4culture.de/id/E4255",
    "schema:MusicComposition": {
        "@id": "https://performance.musiconn.de/work/geistliche-chormusik-singet-frisch-und-wohlgemut-distler-hugo",
        "schema:name": "Geistliche Chormusik. Singet frisch und wohlgemut (Distler, Hugo)",
        "schema:composer": [
            {
                "@type": "schema:Person",
                "@id": {
                    "https://performance.musiconn.de/person/distler-hugo-1908-1942": {
                        "gnd": "https://d-nb.info/gnd/118679848",
                        "viaf": "https://viaf.org/viaf/61586869"
                    }
                }
            }
        ],
        "schema:description": [
            {
                "@value": "Motette auf die Weihnacht f\u00fcr vierstimmigen Chor a cappella"
            }
        ],
        "schema:alternateName": [
            {
                "@value": "Geistliche Chormusik. Singet frisch und wohlgemut"
            },
            {
                "@value": "Singet frisch und wohlgemut"
            },
            {
                "@value": "Nun singet frisch und wohlgemut"
            },
            {
                "@value": "Geistliche Chormusik, op. 12,4"
            }
        ],
        "schema:genre": [
            {
                "@id": {
                    "https://performance.musiconn.de/subject/motette": {
                        "gnd": "https://d-nb.info/gnd/4040357-9",
                        "viaf": null
                    }
                }
            }
        ],
        "schema:includedComposition": [],
        "schema:subjectOf": [],
        "schema:contributor": [
            {
                "@type": "schema:PerformingGroup",
                "@id": {
                    "https://performance.musiconn.de/corporation/dresdner-kreuzchor": {
                        "gnd": "https://d-nb.info/gnd/2074419-5",
                        "viaf": "https://viaf.org/viaf/139053206"
                    }
                }
            },
            {
                "@type": "schema:PerformingGroup",
                "@id": {
                    "https://performance.musiconn.de/corporation/thomanerchor-leipzig": {
                        "gnd": "https://d-nb.info/gnd/1212749-8",
                        "viaf": "https://viaf.org/viaf/150245159"
                    }
                }
            }
        ]
    }
}