{
    "@context": {
        "schema": "http://schema.org/"
    },
    "@id": "https://nfdi4culture.de/id/E4255",
    "schema:MusicComposition": {
        "@id": "https://performance.musiconn.de/work/chant-du-voyageur-paderewski-ignacy-jan",
        "schema:name": "Chant du voyageur (Paderewski, Ignacy Jan)",
        "schema:composer": [
            {
                "@type": "schema:Person",
                "@id": {
                    "https://performance.musiconn.de/person/paderewski-ignacy-jan-1860-1941": {
                        "gnd": "https://d-nb.info/gnd/118986724",
                        "viaf": "https://viaf.org/viaf/76501096"
                    }
                }
            }
        ],
        "schema:description": [
            {
                "@value": "Unklar, welches Werk"
            }
        ],
        "schema:alternateName": [
            {
                "@value": "Chant du voyageur"
            }
        ],
        "schema:genre": [
            {
                "@id": {
                    "https://performance.musiconn.de/subject/klaviermusik": {
                        "gnd": "https://d-nb.info/gnd/4030993-9",
                        "viaf": null
                    }
                }
            }
        ],
        "schema:includedComposition": [],
        "schema:subjectOf": [
            {
                "@type": "schema:event",
                "@id": {
                    "https://performance.musiconn.de/event/concert-mit-orchester-von-margarete-stern-gewerbehaus-dresden-gewerbehaus-saal-1889-11-20-19-00": {
                        "gnd": null,
                        "viaf": null
                    }
                }
            }
        ],
        "schema:contributor": [
            {
                "@type": "schema:Person",
                "@id": {
                    "https://performance.musiconn.de/person/stern-margarethe-1857-1899": {
                        "gnd": "https://d-nb.info/gnd/117276693",
                        "viaf": "https://viaf.org/viaf/32769830"
                    }
                }
            }
        ]
    }
}