{
    "@context": {
        "schema": "http://schema.org/"
    },
    "@id": "https://nfdi4culture.de/id/E4255",
    "schema:MusicComposition": {
        "@id": "https://performance.musiconn.de/work/rondos-violine-klavier-d-895-h-moll-schubert-franz",
        "schema:name": "Rondos, Violine, Klavier, D 895 (h-Moll) (Schubert, Franz)",
        "schema:composer": [
            {
                "@type": "schema:Person",
                "@id": {
                    "https://performance.musiconn.de/person/schubert-franz-1797-1828": {
                        "gnd": "https://d-nb.info/gnd/118610961",
                        "viaf": "https://viaf.org/viaf/29719275"
                    }
                }
            }
        ],
        "schema:description": [],
        "schema:alternateName": [
            {
                "@value": "Rondos, Violine, Klavier, D 895 (h-Moll)"
            },
            {
                "@value": "Rondos, Violine, Klavier, op. 70 (h-Moll)"
            },
            {
                "@value": "Rondeau brilliant pour pianoforte et violon Op: 70"
            },
            {
                "@value": "Rondos, Vl, Kl, D 895"
            }
        ],
        "schema:genre": [
            {
                "@id": {
                    "https://performance.musiconn.de/subject/rondo": {
                        "gnd": "https://d-nb.info/gnd/4178454-6",
                        "viaf": null
                    }
                }
            }
        ],
        "schema:includedComposition": [],
        "schema:subjectOf": [],
        "schema:contributor": [
            {
                "@type": "schema:Person",
                "@id": {
                    "https://performance.musiconn.de/person/bargheer-adolf-1840-1901": {
                        "gnd": "https://d-nb.info/gnd/1251767842",
                        "viaf": "https://viaf.org/viaf/44152742895627730847"
                    }
                }
            },
            {
                "@type": "schema:Person",
                "@id": {
                    "https://performance.musiconn.de/person/beroff-michel-1950": {
                        "gnd": "https://d-nb.info/gnd/123995108",
                        "viaf": "https://viaf.org/viaf/95314391"
                    }
                }
            },
            {
                "@type": "schema:Person",
                "@id": {
                    "https://performance.musiconn.de/person/bronsart-von-schellendorf-hans-1830-1913": {
                        "gnd": "https://d-nb.info/gnd/117735728",
                        "viaf": "https://viaf.org/viaf/62333906"
                    }
                }
            },
            {
                "@type": "schema:Person",
                "@id": {
                    "https://performance.musiconn.de/person/damrosch-leopold-1832-1885": {
                        "gnd": "https://d-nb.info/gnd/116020768",
                        "viaf": "https://viaf.org/viaf/66730233"
                    }
                }
            },
            {
                "@type": "schema:Person",
                "@id": {
                    "https://performance.musiconn.de/person/grimm-julius-otto-1827-1903": {
                        "gnd": "https://d-nb.info/gnd/116843217",
                        "viaf": "https://viaf.org/viaf/54910787"
                    }
                }
            },
            {
                "@type": "schema:Person",
                "@id": {
                    "https://performance.musiconn.de/person/hansen-cecilia-1897-1989": {
                        "gnd": "https://d-nb.info/gnd/1159798354",
                        "viaf": "https://viaf.org/viaf/78569879"
                    }
                }
            },
            {
                "@type": "schema:Person",
                "@id": {
                    "https://performance.musiconn.de/person/hoelscher-ulf-1942": {
                        "gnd": "https://d-nb.info/gnd/122080874",
                        "viaf": "https://viaf.org/viaf/115730793"
                    }
                }
            },
            {
                "@type": "schema:Person",
                "@id": {
                    "https://performance.musiconn.de/person/sacharoff-boris": {
                        "gnd": null,
                        "viaf": null
                    }
                }
            }
        ]
    }
}