{
    "@context": {
        "schema": "http://schema.org/"
    },
    "@id": "https://nfdi4culture.de/id/E4255",
    "schema:MusicComposition": {
        "@id": "https://performance.musiconn.de/work/italienisches-liederbuch-lied-wolf-hugo",
        "schema:name": "Italienisches Liederbuch. Lied (Wolf, Hugo)",
        "schema:composer": [
            {
                "@type": "schema:Person",
                "@id": {
                    "https://performance.musiconn.de/person/wolf-hugo-1860-1903": {
                        "gnd": "https://d-nb.info/gnd/118634712",
                        "viaf": "https://viaf.org/viaf/120704169"
                    }
                }
            }
        ],
        "schema:description": [
            {
                "@value": "Unklar, welches"
            }
        ],
        "schema:alternateName": [
            {
                "@value": "Italienisches Liederbuch. Lied"
            },
            {
                "@value": "Aus dem \"Italienischen Liederbuch\""
            }
        ],
        "schema:genre": [],
        "schema:includedComposition": [],
        "schema:subjectOf": [],
        "schema:contributor": [
            {
                "@type": "schema:PerformingGroup",
                "@id": {
                    "https://performance.musiconn.de/corporation/dresdner-philharmonie": {
                        "gnd": "https://d-nb.info/gnd/815129-5",
                        "viaf": "https://viaf.org/viaf/133022259"
                    }
                }
            }
        ]
    }
}