{
    "@context": {
        "schema": "http://schema.org/"
    },
    "@id": "https://nfdi4culture.de/id/E4255",
    "schema:MusicComposition": {
        "@id": "https://performance.musiconn.de/work/andante-dauthage-max",
        "schema:name": "Andante (Dauthage, Max)",
        "schema:composer": [
            {
                "@type": "schema:Person",
                "@id": {
                    "https://performance.musiconn.de/person/dauthage-max-1862-1937": {
                        "gnd": "https://d-nb.info/gnd/134721810",
                        "viaf": "https://viaf.org/viaf/68532560"
                    }
                }
            }
        ],
        "schema:description": [],
        "schema:alternateName": [
            {
                "@value": "Andante"
            },
            {
                "@value": "Andante op. posth. f\u00fcr vier Kontrab\u00e4sse"
            }
        ],
        "schema:genre": [],
        "schema:includedComposition": [],
        "schema:subjectOf": [],
        "schema:contributor": [
            {
                "@type": "schema:Person",
                "@id": {
                    "https://performance.musiconn.de/person/ermold-thilo": {
                        "gnd": null,
                        "viaf": null
                    }
                }
            },
            {
                "@type": "schema:Person",
                "@id": {
                    "https://performance.musiconn.de/person/gloeckler-tobias": {
                        "gnd": "https://d-nb.info/gnd/134883241",
                        "viaf": "https://viaf.org/viaf/66072717"
                    }
                }
            },
            {
                "@type": "schema:Person",
                "@id": {
                    "https://performance.musiconn.de/person/hoppe-roland": {
                        "gnd": null,
                        "viaf": null
                    }
                }
            },
            {
                "@type": "schema:Person",
                "@id": {
                    "https://performance.musiconn.de/person/schuster-norbert": {
                        "gnd": "https://d-nb.info/gnd/128636289",
                        "viaf": "https://viaf.org/viaf/101086795"
                    }
                }
            }
        ]
    }
}