{
    "@context": {
        "schema": "http://schema.org/"
    },
    "@id": "https://nfdi4culture.de/id/E4255",
    "schema:MusicComposition": {
        "@id": "https://performance.musiconn.de/work/stuecke-violine-klavier-op-7-webern-anton",
        "schema:name": "St\u00fccke, Violine, Klavier, op. 7 (Webern, Anton)",
        "schema:composer": [
            {
                "@type": "schema:Person",
                "@id": {
                    "https://performance.musiconn.de/person/webern-anton-1883-1945": {
                        "gnd": "https://d-nb.info/gnd/118629786",
                        "viaf": "https://viaf.org/viaf/22329168"
                    }
                }
            }
        ],
        "schema:description": [],
        "schema:alternateName": [
            {
                "@value": "St\u00fccke, Violine, Klavier, op. 7"
            },
            {
                "@value": "St\u00fccke, Vl, Kl, op. 7"
            },
            {
                "@value": "St\u00fccke, Vl Kl op. 7"
            },
            {
                "@value": "Vier St\u00fccke f\u00fcr Violine und Klavier, op. 7"
            }
        ],
        "schema:genre": [
            {
                "@id": {
                    "https://performance.musiconn.de/subject/instrumentalstueck": {
                        "gnd": "https://d-nb.info/gnd/7727983-9",
                        "viaf": null
                    }
                }
            }
        ],
        "schema:includedComposition": [],
        "schema:subjectOf": [],
        "schema:contributor": [
            {
                "@type": "schema:Person",
                "@id": {
                    "https://performance.musiconn.de/person/altenburger-christian-1957": {
                        "gnd": "https://d-nb.info/gnd/128870125",
                        "viaf": "https://viaf.org/viaf/56808955"
                    }
                }
            },
            {
                "@type": "schema:Person",
                "@id": {
                    "https://performance.musiconn.de/person/broemsel-ralf-carsten-1956": {
                        "gnd": "https://d-nb.info/gnd/135054176",
                        "viaf": "https://viaf.org/viaf/78328076"
                    }
                }
            },
            {
                "@type": "schema:Person",
                "@id": {
                    "https://performance.musiconn.de/person/glaetzer-udo": {
                        "gnd": null,
                        "viaf": null
                    }
                }
            },
            {
                "@type": "schema:Person",
                "@id": {
                    "https://performance.musiconn.de/person/mauser-siegfried-1954": {
                        "gnd": "https://d-nb.info/gnd/115484183",
                        "viaf": "https://viaf.org/viaf/59181056"
                    }
                }
            }
        ]
    }
}