{
    "@context": {
        "schema": "http://schema.org/"
    },
    "@id": "https://nfdi4culture.de/id/E4255",
    "schema:MusicComposition": {
        "@id": "https://performance.musiconn.de/work/konzerte-streichorchester-k-75-d-dur-stravinsky-igor",
        "schema:name": "Konzerte, Streichorchester, K 75 (D-Dur) (Stravinsky, Igor)",
        "schema:composer": [
            {
                "@type": "schema:Person",
                "@id": {
                    "https://performance.musiconn.de/person/stravinsky-igor-1882-1971": {
                        "gnd": "https://d-nb.info/gnd/118642545",
                        "viaf": "https://viaf.org/viaf/17309155"
                    }
                }
            }
        ],
        "schema:description": [],
        "schema:alternateName": [
            {
                "@value": "Konzerte, Streichorchester, K 75 (D-Dur)"
            },
            {
                "@value": "Konzerte, Streichorch, K 75"
            },
            {
                "@value": "Basle concerto"
            },
            {
                "@value": "Basler Concerto"
            },
            {
                "@value": "Konzerte, Orch (D-Dur)"
            },
            {
                "@value": "Konzert f\u00fcr Streicher in D"
            }
        ],
        "schema:genre": [
            {
                "@id": {
                    "https://performance.musiconn.de/subject/konzert": {
                        "gnd": "https://d-nb.info/gnd/4032359-6",
                        "viaf": null
                    }
                }
            }
        ],
        "schema:includedComposition": [],
        "schema:subjectOf": [],
        "schema:contributor": [
            {
                "@type": "schema:PerformingGroup",
                "@id": {
                    "https://performance.musiconn.de/corporation/dresdner-philharmonie": {
                        "gnd": "https://d-nb.info/gnd/815129-5",
                        "viaf": "https://viaf.org/viaf/133022259"
                    }
                }
            },
            {
                "@type": "schema:PerformingGroup",
                "@id": {
                    "https://performance.musiconn.de/corporation/gosudarstvennyj-simfoniceskij-orkestr-leningradskoj-filarmonii-kamernyj-orkestr": {
                        "gnd": "https://d-nb.info/gnd/5209677-4",
                        "viaf": "https://viaf.org/viaf/311114716"
                    }
                }
            },
            {
                "@type": "schema:PerformingGroup",
                "@id": {
                    "https://performance.musiconn.de/corporation/philharmonisches-kammerorchester-dresden": {
                        "gnd": "https://d-nb.info/gnd/5333671-9",
                        "viaf": "https://viaf.org/viaf/133420726"
                    }
                }
            }
        ]
    }
}