{
    "@context": {
        "schema": "http://schema.org/"
    },
    "@id": "https://nfdi4culture.de/id/E4255",
    "schema:MusicComposition": {
        "@id": "https://performance.musiconn.de/work/concerto-grosso-f-dur-op-41-lederer-joseph",
        "schema:name": "Concerto grosso F-Dur op. 41 (Lederer, Joseph)",
        "schema:composer": [
            {
                "@type": "schema:Person",
                "@id": {
                    "https://performance.musiconn.de/person/lederer-joseph-1877-1958": {
                        "gnd": "https://d-nb.info/gnd/142514241",
                        "viaf": "https://viaf.org/viaf/130955660"
                    }
                }
            }
        ],
        "schema:description": [],
        "schema:alternateName": [
            {
                "@value": "Concerto grosso F-Dur op. 41"
            }
        ],
        "schema:genre": [],
        "schema:includedComposition": [],
        "schema:subjectOf": [],
        "schema:contributor": [
            {
                "@type": "schema:Person",
                "@id": {
                    "https://performance.musiconn.de/person/kutzschbach-hermann-1875-1938": {
                        "gnd": "https://d-nb.info/gnd/116631821",
                        "viaf": "https://viaf.org/viaf/10602206"
                    }
                }
            }
        ]
    }
}