{
    "@context": {
        "schema": "http://schema.org/"
    },
    "@id": "https://nfdi4culture.de/id/E4255",
    "schema:MusicComposition": {
        "@id": "https://performance.musiconn.de/work/di-maschke-fueting-reiko-gordon-michl",
        "schema:name": "Di maschke (F\u00fcting, Reiko, Gordon, Michl)",
        "schema:composer": [
            {
                "@type": "schema:Person",
                "@id": {
                    "https://performance.musiconn.de/person/fueting-reiko-1970": {
                        "gnd": "https://d-nb.info/gnd/135189020",
                        "viaf": "https://viaf.org/viaf/80019148"
                    }
                }
            },
            {
                "@type": "schema:Person",
                "@id": {
                    "https://performance.musiconn.de/person/gordon-michl-1823-1890": {
                        "gnd": null,
                        "viaf": null
                    }
                }
            }
        ],
        "schema:description": [
            {
                "@value": "arrangiert von Reiko F\u00fcting"
            }
        ],
        "schema:alternateName": [
            {
                "@value": "Di maschke"
            },
            {
                "@value": "Di mashke"
            }
        ],
        "schema:genre": [
            {
                "@id": {
                    "https://performance.musiconn.de/subject/chormusik": {
                        "gnd": "https://d-nb.info/gnd/4131189-9",
                        "viaf": null
                    }
                }
            }
        ],
        "schema:includedComposition": [],
        "schema:subjectOf": [],
        "schema:contributor": []
    }
}