{
    "@context": {
        "schema": "http://schema.org/"
    },
    "@id": "https://nfdi4culture.de/id/E4255",
    "schema:MusicComposition": {
        "@id": "https://performance.musiconn.de/work/le-nozze-di-figaro-arie-der-graefin-f-dur-mozart-wolfgang-amadeus",
        "schema:name": "Le nozze di Figaro. Arie der Gr\u00e4fin (F-Dur) (Mozart, Wolfgang Amadeus)",
        "schema:composer": [
            {
                "@type": "schema:Person",
                "@id": {
                    "https://performance.musiconn.de/person/mozart-wolfgang-amadeus-1756-1791": {
                        "gnd": "https://d-nb.info/gnd/118584596",
                        "viaf": "https://viaf.org/viaf/32197206"
                    }
                }
            }
        ],
        "schema:description": [
            {
                "@value": "F-Dur-Arie der Gr\u00e4fin aus Figaros Hochzeit"
            }
        ],
        "schema:alternateName": [
            {
                "@value": "Le nozze di Figaro. Arie der Gr\u00e4fin (F-Dur)"
            }
        ],
        "schema:genre": [
            {
                "@id": {
                    "https://performance.musiconn.de/subject/arie": {
                        "gnd": "https://d-nb.info/gnd/4143006-2",
                        "viaf": null
                    }
                }
            }
        ],
        "schema:includedComposition": [],
        "schema:subjectOf": [],
        "schema:contributor": [
            {
                "@type": "schema:PerformingGroup",
                "@id": {
                    "https://performance.musiconn.de/corporation/euterpe-orchester-leipzig": {
                        "gnd": null,
                        "viaf": null
                    }
                }
            }
        ]
    }
}