{
    "@context": {
        "schema": "http://schema.org/"
    },
    "@id": "https://nfdi4culture.de/id/E4255",
    "schema:MusicComposition": {
        "@id": "https://performance.musiconn.de/work/solnce-inkov-denisov-edison-vasilevic",
        "schema:name": "Solnce inkov (Denisov, \u0116dison Vasil'evi\u010d)",
        "schema:composer": [
            {
                "@type": "schema:Person",
                "@id": {
                    "https://performance.musiconn.de/person/denisov-edison-vasilevic-1929-1996": {
                        "gnd": "https://d-nb.info/gnd/118990241",
                        "viaf": "https://viaf.org/viaf/113018146"
                    }
                }
            }
        ],
        "schema:description": [],
        "schema:alternateName": [
            {
                "@value": "Solnce inkov"
            },
            {
                "@value": "Die Sonne der Inkas"
            }
        ],
        "schema:genre": [
            {
                "@id": {
                    "https://performance.musiconn.de/subject/kammermusik": {
                        "gnd": "https://d-nb.info/gnd/4136998-1",
                        "viaf": null
                    }
                }
            }
        ],
        "schema:includedComposition": [],
        "schema:subjectOf": [],
        "schema:contributor": [
            {
                "@type": "schema:PerformingGroup",
                "@id": {
                    "https://performance.musiconn.de/corporation/gosudarstvennyj-akademiceskij-bolsoj-teatr-sojuza-ssr-orkestr-ansambl-solistov": {
                        "gnd": "https://d-nb.info/gnd/10303915-6",
                        "viaf": "https://viaf.org/viaf/308696383"
                    }
                }
            }
        ]
    }
}