{
    "@context": {
        "schema": "http://schema.org/"
    },
    "@id": "https://nfdi4culture.de/id/E4255",
    "schema:MusicComposition": {
        "@id": "https://performance.musiconn.de/work/radiant-voices-ticheli-frank",
        "schema:name": "Radiant voices (Ticheli, Frank)",
        "schema:composer": [
            {
                "@type": "schema:Person",
                "@id": {
                    "https://performance.musiconn.de/person/ticheli-frank-1958": {
                        "gnd": "https://d-nb.info/gnd/134890175",
                        "viaf": "https://viaf.org/viaf/79838369"
                    }
                }
            }
        ],
        "schema:description": [],
        "schema:alternateName": [
            {
                "@value": "Radiant voices"
            }
        ],
        "schema:genre": [],
        "schema:includedComposition": [],
        "schema:subjectOf": [],
        "schema:contributor": [
            {
                "@type": "schema:PerformingGroup",
                "@id": {
                    "https://performance.musiconn.de/corporation/frankfurter-opernhaus-und-museumsorchester": {
                        "gnd": "https://d-nb.info/gnd/1078513163",
                        "viaf": "https://viaf.org/viaf/45144814273718687574"
                    }
                }
            }
        ]
    }
}