{
    "@context": {
        "schema": "http://schema.org/"
    },
    "@id": "https://nfdi4culture.de/id/E4255",
    "schema:MusicComposition": {
        "@id": "https://performance.musiconn.de/work/scherzi-orchester-goldmark-karl",
        "schema:name": "Scherzi, Orchester (Goldmark, Karl)",
        "schema:composer": [
            {
                "@type": "schema:Person",
                "@id": {
                    "https://performance.musiconn.de/person/goldmark-karl-1830-1915": {
                        "gnd": "https://d-nb.info/gnd/119527995",
                        "viaf": "https://viaf.org/viaf/42025332"
                    }
                }
            }
        ],
        "schema:description": [
            {
                "@value": "Unklar, ob op. 19 oder op. 45 gemeint ist"
            }
        ],
        "schema:alternateName": [
            {
                "@value": "Scherzi, Orchester"
            }
        ],
        "schema:genre": [
            {
                "@id": {
                    "https://performance.musiconn.de/subject/scherzo": {
                        "gnd": "https://d-nb.info/gnd/4179504-0",
                        "viaf": null
                    }
                }
            }
        ],
        "schema:includedComposition": [],
        "schema:subjectOf": [],
        "schema:contributor": [
            {
                "@type": "schema:PerformingGroup",
                "@id": {
                    "https://performance.musiconn.de/corporation/verein-hamburgischer-musikfreunde": {
                        "gnd": "https://d-nb.info/gnd/365223-3",
                        "viaf": "https://viaf.org/viaf/131976266"
                    }
                }
            }
        ]
    }
}