{
    "@context": {
        "schema": "http://schema.org/"
    },
    "@id": "https://nfdi4culture.de/id/E4255",
    "schema:MusicComposition": {
        "@id": "https://performance.musiconn.de/work/duos-floete-viola-op-21-1-g-dur-hoffmeister-franz-anton",
        "schema:name": "Duos, Fl\u00f6te, Viola, op. 21/1 (G-Dur) (Hoffmeister, Franz Anton)",
        "schema:composer": [
            {
                "@type": "schema:Person",
                "@id": {
                    "https://performance.musiconn.de/person/hoffmeister-franz-anton-1754-1812": {
                        "gnd": "https://d-nb.info/gnd/119060922",
                        "viaf": "https://viaf.org/viaf/24787388"
                    }
                }
            }
        ],
        "schema:description": [],
        "schema:alternateName": [
            {
                "@value": "Duos, Fl\u00f6te, Viola, op. 21/1 (G-Dur)"
            }
        ],
        "schema:genre": [],
        "schema:includedComposition": [],
        "schema:subjectOf": [],
        "schema:contributor": [
            {
                "@type": "schema:Person",
                "@id": {
                    "https://performance.musiconn.de/person/causse-gerard-1948": {
                        "gnd": "https://d-nb.info/gnd/128662182",
                        "viaf": "https://viaf.org/viaf/46945818"
                    }
                }
            },
            {
                "@type": "schema:Person",
                "@id": {
                    "https://performance.musiconn.de/person/grafenauer-irena": {
                        "gnd": "https://d-nb.info/gnd/131386247",
                        "viaf": "https://viaf.org/viaf/66653771"
                    }
                }
            }
        ]
    }
}