{
    "@context": {
        "schema": "http://schema.org/"
    },
    "@id": "https://nfdi4culture.de/id/E4255",
    "schema:MusicComposition": {
        "@id": "https://performance.musiconn.de/work/lieder-h-26a31-36-she-never-told-her-love-haydn-joseph",
        "schema:name": "Lieder, H 26a,31 - 36. She never told her love (Haydn, Joseph)",
        "schema:composer": [
            {
                "@type": "schema:Person",
                "@id": {
                    "https://performance.musiconn.de/person/haydn-joseph-1732-1809": {
                        "gnd": "https://d-nb.info/gnd/118547356",
                        "viaf": "https://viaf.org/viaf/95146280"
                    }
                }
            }
        ],
        "schema:description": [],
        "schema:alternateName": [
            {
                "@value": "Lieder, H 26a,31 - 36. She never told her love"
            },
            {
                "@value": "Die Liebe trug sie stumm"
            }
        ],
        "schema:genre": [
            {
                "@id": {
                    "https://performance.musiconn.de/subject/lied": {
                        "gnd": "https://d-nb.info/gnd/4035669-3",
                        "viaf": null
                    }
                }
            }
        ],
        "schema:includedComposition": [],
        "schema:subjectOf": [],
        "schema:contributor": [
            {
                "@type": "schema:Person",
                "@id": {
                    "https://performance.musiconn.de/person/miller-lajos-1940": {
                        "gnd": "https://d-nb.info/gnd/133114902",
                        "viaf": "https://viaf.org/viaf/114825124"
                    }
                }
            }
        ]
    }
}