{
    "@context": {
        "schema": "http://schema.org/"
    },
    "@id": "https://nfdi4culture.de/id/E4255",
    "schema:MusicComposition": {
        "@id": "https://performance.musiconn.de/work/la-cenerentola-fassung-rossini-gioachino",
        "schema:name": "La Cenerentola / Fassung (Rossini, Gioachino)",
        "schema:composer": [
            {
                "@type": "schema:Person",
                "@id": {
                    "https://performance.musiconn.de/person/rossini-gioachino-1792-1868": {
                        "gnd": "https://d-nb.info/gnd/118602985",
                        "viaf": "https://viaf.org/viaf/34644407"
                    }
                }
            }
        ],
        "schema:description": [
            {
                "@value": "\u00dcbersetzt und bearbeitet von Karl von Holtei"
            }
        ],
        "schema:alternateName": [
            {
                "@value": "La Cenerentola / Fassung"
            },
            {
                "@value": "Aschenbr\u00f6del oder der Triumph nach Herzensg\u00fcte"
            }
        ],
        "schema:genre": [
            {
                "@id": {
                    "https://performance.musiconn.de/subject/komische-oper": {
                        "gnd": "https://d-nb.info/gnd/4164762-2",
                        "viaf": null
                    }
                }
            }
        ],
        "schema:includedComposition": [],
        "schema:subjectOf": [],
        "schema:contributor": [
            {
                "@type": "schema:Person",
                "@id": {
                    "https://performance.musiconn.de/person/bamberger-eva-1811": {
                        "gnd": "https://d-nb.info/gnd/130655600",
                        "viaf": "https://viaf.org/viaf/67580253"
                    }
                }
            },
            {
                "@type": "schema:Person",
                "@id": {
                    "https://performance.musiconn.de/person/felsenheim-charlotte": {
                        "gnd": "https://d-nb.info/gnd/1050465849",
                        "viaf": "https://viaf.org/viaf/308204039"
                    }
                }
            },
            {
                "@type": "schema:Person",
                "@id": {
                    "https://performance.musiconn.de/person/forti-anton-1790-1859": {
                        "gnd": "https://d-nb.info/gnd/13600363X",
                        "viaf": "https://viaf.org/viaf/80421698"
                    }
                }
            },
            {
                "@type": "schema:Person",
                "@id": {
                    "https://performance.musiconn.de/person/genee-friedrich-1795-1856": {
                        "gnd": "https://d-nb.info/gnd/116540494",
                        "viaf": "https://viaf.org/viaf/72147800"
                    }
                }
            },
            {
                "@type": "schema:Person",
                "@id": {
                    "https://performance.musiconn.de/person/jaeger-franz-1792-1852": {
                        "gnd": "https://d-nb.info/gnd/1012275701",
                        "viaf": "https://viaf.org/viaf/234154592501143370004"
                    }
                }
            },
            {
                "@type": "schema:Person",
                "@id": {
                    "https://performance.musiconn.de/person/muehlenbruch-katharina-1842": {
                        "gnd": "https://d-nb.info/gnd/117162477",
                        "viaf": "https://viaf.org/viaf/22912028"
                    }
                }
            },
            {
                "@type": "schema:Person",
                "@id": {
                    "https://performance.musiconn.de/person/mueller-lida": {
                        "gnd": "https://d-nb.info/gnd/1057769797",
                        "viaf": "https://viaf.org/viaf/310598502"
                    }
                }
            },
            {
                "@type": "schema:Person",
                "@id": {
                    "https://performance.musiconn.de/person/sontag-henriette-1806-1854": {
                        "gnd": "https://d-nb.info/gnd/118797999",
                        "viaf": "https://viaf.org/viaf/69198419"
                    }
                }
            },
            {
                "@type": "schema:Person",
                "@id": {
                    "https://performance.musiconn.de/person/spitzeder-betty-1808-1872": {
                        "gnd": "https://d-nb.info/gnd/132425831",
                        "viaf": "https://viaf.org/viaf/6093929"
                    }
                }
            },
            {
                "@type": "schema:Person",
                "@id": {
                    "https://performance.musiconn.de/person/spitzeder-josef-1796-1832": {
                        "gnd": "https://d-nb.info/gnd/117483478",
                        "viaf": "https://viaf.org/viaf/20458672"
                    }
                }
            },
            {
                "@type": "schema:Person",
                "@id": {
                    "https://performance.musiconn.de/person/waechter-johann-michael-1794-1853": {
                        "gnd": "https://d-nb.info/gnd/117086940",
                        "viaf": "https://viaf.org/viaf/37684413"
                    }
                }
            }
        ]
    }
}