{
    "@context": {
        "schema": "http://schema.org/"
    },
    "@id": "https://nfdi4culture.de/id/E4255",
    "schema:MusicComposition": {
        "@id": "https://performance.musiconn.de/work/mein-herz-fuer-diese-stadt-lied-ueber-dresden-grafe-manfred",
        "schema:name": "Mein Herz f\u00fcr diese Stadt. Lied \u00fcber Dresden (Grafe, Manfred)",
        "schema:composer": [
            {
                "@type": "schema:Person",
                "@id": {
                    "https://performance.musiconn.de/person/grafe-manfred-1935-2013": {
                        "gnd": "https://d-nb.info/gnd/133552462",
                        "viaf": "https://viaf.org/viaf/119900192"
                    }
                }
            }
        ],
        "schema:description": [],
        "schema:alternateName": [
            {
                "@value": "Mein Herz f\u00fcr diese Stadt. Lied \u00fcber Dresden"
            }
        ],
        "schema:genre": [],
        "schema:includedComposition": [],
        "schema:subjectOf": [],
        "schema:contributor": [
            {
                "@type": "schema:Person",
                "@id": {
                    "https://performance.musiconn.de/person/grafe-manfred-1935-2013": {
                        "gnd": "https://d-nb.info/gnd/133552462",
                        "viaf": "https://viaf.org/viaf/119900192"
                    }
                }
            }
        ]
    }
}