{
    "@context": {
        "schema": "http://schema.org/"
    },
    "@id": "https://nfdi4culture.de/id/E4255",
    "schema:MusicComposition": {
        "@id": "https://performance.musiconn.de/work/la-pastorella-mia-arcadelt-jacob",
        "schema:name": "La pastorella mia (Arcadelt, Jacob)",
        "schema:composer": [
            {
                "@type": "schema:Person",
                "@id": {
                    "https://performance.musiconn.de/person/arcadelt-jacob-1504-1568": {
                        "gnd": "https://d-nb.info/gnd/119501716",
                        "viaf": "https://viaf.org/viaf/61730880"
                    }
                }
            }
        ],
        "schema:description": [
            {
                "@value": "Ver\u00f6ffentlicht in: Tiers livre de chansons, nouvellement mises en musique..., Paris, Le Roy et Ballard, 1554"
            }
        ],
        "schema:alternateName": [
            {
                "@value": "La pastorella mia"
            },
            {
                "@value": "La Pastorella mia"
            },
            {
                "@value": "Madrigale. La pastorella mia"
            }
        ],
        "schema:genre": [
            {
                "@id": {
                    "https://performance.musiconn.de/subject/madrigal": {
                        "gnd": "https://d-nb.info/gnd/4168452-7",
                        "viaf": null
                    }
                }
            }
        ],
        "schema:includedComposition": [],
        "schema:subjectOf": [],
        "schema:contributor": []
    }
}