{
    "@context": {
        "schema": "http://schema.org/"
    },
    "@id": "https://nfdi4culture.de/id/E4255",
    "schema:event": {
        "@id": "https://performance.musiconn.de/event/konzert-schloss-wilhelmsburg-schmalkalden-1978-06-30",
        "schema:name": "Konzert, Schloss Wilhelmsburg (Schmalkalden), 30.6.1978",
        "schema:location": {
            "https://performance.musiconn.de/location/schloss-wilhelmsburg-schmalkalden": {
                "gnd": "https://d-nb.info/gnd/4272463-6",
                "viaf": "https://viaf.org/viaf/234707092"
            }
        },
        "schema:temporalCoverage": {
            "@type": "schema:DateTime",
            "@value": "1978-06-30/1978-06-30"
        },
        "schema:alternateName": [
            {
                "@value": "Konzert"
            },
            {
                "@value": "anl\u00e4sslich des Folklore-Festivals der 17. Arbeiterfestspiele der DDR"
            }
        ],
        "schema:superEvent": [
            {
                "@type": "schema:Event",
                "@id": {}
            }
        ],
        "schema:recordedIn": [
            {
                "@id": {
                    "https://performance.musiconn.de/source/motettenbuch-1978": {
                        "gnd": null,
                        "viaf": null
                    }
                }
            }
        ],
        "schema:performer": [],
        "schema:workPerformed": [
            {
                "@id": {
                    "https://performance.musiconn.de/work/lustgarten-neuer-teutscher-gesaeng-nun-fanget-an-hassler-hans-leo": {
                        "gnd": null,
                        "viaf": null
                    }
                },
                "schema:author": [
                    {
                        "@type": "schema:Person",
                        "@id": {
                            "https://performance.musiconn.de/person/hassler-hans-leo-1564-1612": {
                                "gnd": "https://d-nb.info/gnd/118917447",
                                "viaf": "https://viaf.org/viaf/76500260"
                            }
                        }
                    }
                ]
            },
            {
                "@id": {
                    "https://performance.musiconn.de/work/weltspiegel-das-ist-neue-teutsche-gesaenger-sampt-zweyen-canzonen-o-musica-peuerl-paul": {
                        "gnd": null,
                        "viaf": null
                    }
                },
                "schema:author": [
                    {
                        "@type": "schema:Person",
                        "@id": {
                            "https://performance.musiconn.de/person/peuerl-paul-1570-1625": {
                                "gnd": "https://d-nb.info/gnd/101383592",
                                "viaf": "https://viaf.org/viaf/54338122"
                            }
                        }
                    }
                ]
            },
            {
                "@id": {
                    "https://performance.musiconn.de/work/singet-dem-herrn-ein-neues-lied-bwv-225-bach-johann-sebastian": {
                        "gnd": "https://d-nb.info/gnd/300009941",
                        "viaf": "https://viaf.org/viaf/181241390"
                    }
                },
                "schema:author": [
                    {
                        "@type": "schema:Person",
                        "@id": {
                            "https://performance.musiconn.de/person/bach-johann-sebastian-1685-1750": {
                                "gnd": "https://d-nb.info/gnd/11850553X",
                                "viaf": "https://viaf.org/viaf/12304462"
                            }
                        }
                    }
                ]
            },
            {
                "@id": {
                    "https://performance.musiconn.de/work/lieder-und-romanzen-op-93a-der-bucklichte-fiedler-brahms-johannes": {
                        "gnd": "https://d-nb.info/gnd/300629133",
                        "viaf": "https://viaf.org/viaf/185713556"
                    }
                },
                "schema:author": [
                    {
                        "@type": "schema:Person",
                        "@id": {
                            "https://performance.musiconn.de/person/brahms-johannes-1833-1897": {
                                "gnd": "https://d-nb.info/gnd/118514253",
                                "viaf": "https://viaf.org/viaf/7573295"
                            }
                        }
                    }
                ]
            },
            {
                "@id": {
                    "https://performance.musiconn.de/work/lieder-und-romanzen-op-93a-das-maedchen-brahms-johannes": {
                        "gnd": "https://d-nb.info/gnd/1058578537",
                        "viaf": "https://viaf.org/viaf/293465396"
                    }
                },
                "schema:author": [
                    {
                        "@type": "schema:Person",
                        "@id": {
                            "https://performance.musiconn.de/person/brahms-johannes-1833-1897": {
                                "gnd": "https://d-nb.info/gnd/118514253",
                                "viaf": "https://viaf.org/viaf/7573295"
                            }
                        }
                    }
                ]
            },
            {
                "@id": {
                    "https://performance.musiconn.de/work/bei-tag-und-nacht-pepping-ernst": {
                        "gnd": null,
                        "viaf": null
                    }
                },
                "schema:author": [
                    {
                        "@type": "schema:Person",
                        "@id": {
                            "https://performance.musiconn.de/person/pepping-ernst-1901-1981": {
                                "gnd": "https://d-nb.info/gnd/118739921",
                                "viaf": "https://viaf.org/viaf/116416740"
                            }
                        }
                    }
                ]
            },
            {
                "@id": {
                    "https://performance.musiconn.de/work/ein-wilhelm-busch-zyklus-zur-beherzigung-weismann-wilhelm": {
                        "gnd": null,
                        "viaf": null
                    }
                },
                "schema:author": [
                    {
                        "@type": "schema:Person",
                        "@id": {
                            "https://performance.musiconn.de/person/weismann-wilhelm-1900-1980": {
                                "gnd": "https://d-nb.info/gnd/117287474",
                                "viaf": "https://viaf.org/viaf/44565021"
                            }
                        }
                    }
                ]
            },
            {
                "@id": {
                    "https://performance.musiconn.de/work/ein-wilhelm-busch-zyklus-dies-fuer-den-und-das-fuer-jenen-weismann-wilhelm": {
                        "gnd": null,
                        "viaf": null
                    }
                },
                "schema:author": [
                    {
                        "@type": "schema:Person",
                        "@id": {
                            "https://performance.musiconn.de/person/weismann-wilhelm-1900-1980": {
                                "gnd": "https://d-nb.info/gnd/117287474",
                                "viaf": "https://viaf.org/viaf/44565021"
                            }
                        }
                    }
                ]
            },
            {
                "@id": {
                    "https://performance.musiconn.de/work/winterreise-der-lindenbaum-fassung-chor-schubert-franz": {
                        "gnd": null,
                        "viaf": null
                    }
                },
                "schema:author": [
                    {
                        "@type": "schema:Person",
                        "@id": {
                            "https://performance.musiconn.de/person/schubert-franz-1797-1828": {
                                "gnd": "https://d-nb.info/gnd/118610961",
                                "viaf": "https://viaf.org/viaf/29719275"
                            }
                        }
                    }
                ]
            },
            {
                "@id": {
                    "https://performance.musiconn.de/work/heidenroeslein-werner-heinrich": {
                        "gnd": "https://d-nb.info/gnd/300582587",
                        "viaf": "https://viaf.org/viaf/179226951"
                    }
                },
                "schema:author": [
                    {
                        "@type": "schema:Person",
                        "@id": {
                            "https://performance.musiconn.de/person/werner-heinrich-1800-1833": {
                                "gnd": "https://d-nb.info/gnd/122840313",
                                "viaf": "https://viaf.org/viaf/57505741"
                            }
                        }
                    }
                ]
            },
            {
                "@id": {
                    "https://performance.musiconn.de/work/vogelhochzeit-und-gaensedieb-wangenheim-volker": {
                        "gnd": "https://d-nb.info/gnd/1069884707",
                        "viaf": "https://viaf.org/viaf/315570461"
                    }
                },
                "schema:author": [
                    {
                        "@type": "schema:Person",
                        "@id": {
                            "https://performance.musiconn.de/person/wangenheim-volker-1928-2014": {
                                "gnd": "https://d-nb.info/gnd/124343767",
                                "viaf": "https://viaf.org/viaf/54331231"
                            }
                        }
                    }
                ]
            },
            {
                "@id": {
                    "https://performance.musiconn.de/work/lieder-im-freien-zu-singen-op-59-abschied-vom-walde-mendelssohn-bartholdy-felix": {
                        "gnd": "https://d-nb.info/gnd/300102151",
                        "viaf": "https://viaf.org/viaf/181522651"
                    }
                },
                "schema:author": [
                    {
                        "@type": "schema:Person",
                        "@id": {
                            "https://performance.musiconn.de/person/mendelssohn-bartholdy-felix-1809-1847": {
                                "gnd": "https://d-nb.info/gnd/118580779",
                                "viaf": "https://viaf.org/viaf/2665666"
                            }
                        }
                    }
                ]
            },
            {
                "@id": {
                    "https://performance.musiconn.de/work/lieder-und-romanzen-op-93a-beherzigung-brahms-johannes": {
                        "gnd": "https://d-nb.info/gnd/1070826049",
                        "viaf": "https://viaf.org/viaf/185743441"
                    }
                },
                "schema:author": [
                    {
                        "@type": "schema:Person",
                        "@id": {
                            "https://performance.musiconn.de/person/brahms-johannes-1833-1897": {
                                "gnd": "https://d-nb.info/gnd/118514253",
                                "viaf": "https://viaf.org/viaf/7573295"
                            }
                        }
                    }
                ]
            },
            {
                "@id": {
                    "https://performance.musiconn.de/work/studentenschmaus-holla-gut-gsell-schein-johann-hermann": {
                        "gnd": "https://d-nb.info/gnd/300137346",
                        "viaf": "https://viaf.org/viaf/217005968"
                    }
                },
                "schema:author": [
                    {
                        "@type": "schema:Person",
                        "@id": {
                            "https://performance.musiconn.de/person/schein-johann-hermann-1586-1630": {
                                "gnd": "https://d-nb.info/gnd/118754408",
                                "viaf": "https://viaf.org/viaf/32162502"
                            }
                        }
                    }
                ]
            },
            {
                "@id": {
                    "https://performance.musiconn.de/work/libro-de-villanelle-moresche-et-altre-canzoni-o-la-o-che-bon-eccho-lasso-orlando-di": {
                        "gnd": null,
                        "viaf": "https://viaf.org/viaf/174110202"
                    }
                },
                "schema:author": [
                    {
                        "@type": "schema:Person",
                        "@id": {
                            "https://performance.musiconn.de/person/lasso-orlando-di-1532-1594": {
                                "gnd": "https://d-nb.info/gnd/118569945",
                                "viaf": "https://viaf.org/viaf/23356192"
                            }
                        }
                    }
                ]
            }
        ]
    }
}