{
    "@context": {
        "schema": "http://schema.org/"
    },
    "@id": "https://nfdi4culture.de/id/E4255",
    "schema:event": {
        "@id": "https://performance.musiconn.de/event/kultureller-festakt-neues-rathaus-leipzig-1933-09-11",
        "schema:name": "kultureller Festakt, Neues Rathaus (Leipzig), 11.9.1933",
        "schema:location": {
            "https://performance.musiconn.de/location/neues-rathaus-leipzig": {
                "gnd": "https://d-nb.info/gnd/4392110-3",
                "viaf": "https://viaf.org/viaf/241846216"
            }
        },
        "schema:temporalCoverage": {
            "@type": "schema:DateTime",
            "@value": "1933-09-11/1933-09-11"
        },
        "schema:alternateName": [
            {
                "@value": "kultureller Festakt"
            }
        ],
        "schema:superEvent": [
            {
                "@type": "schema:Event",
                "@id": {}
            }
        ],
        "schema:recordedIn": [
            {
                "@id": {
                    "https://performance.musiconn.de/source/motettenbuch-1933": {
                        "gnd": null,
                        "viaf": null
                    }
                }
            }
        ],
        "schema:performer": [],
        "schema:workPerformed": []
    }
}