{
    "@context": {
        "schema": "http://schema.org/"
    },
    "@id": "https://nfdi4culture.de/id/E4255",
    "schema:event": {
        "@id": "https://performance.musiconn.de/event/3-zykluskonzert-kulturpalast-dresden-2017-11-04-19-30",
        "schema:name": "3. Zykluskonzert, Kulturpalast (Dresden), 4.11.2017, 19:30",
        "schema:location": {
            "https://performance.musiconn.de/location/kulturpalast-dresden": {
                "gnd": "https://d-nb.info/gnd/1060085488",
                "viaf": "https://viaf.org/viaf/311438221"
            }
        },
        "schema:temporalCoverage": {
            "@type": "schema:DateTime",
            "@value": "2017-11-04T19:30:00/2017-11-04T19:30:00"
        },
        "schema:alternateName": [
            {
                "@value": "3. Zykluskonzert"
            }
        ],
        "schema:superEvent": [
            {
                "@type": "schema:Event",
                "@id": {
                    "https://performance.musiconn.de/series/dresdner-philharmonie-spielzeit-2017-2018": {
                        "gnd": null,
                        "viaf": null
                    }
                }
            }
        ],
        "schema:recordedIn": [
            {
                "@id": {
                    "https://performance.musiconn.de/source/konzertarchiv-der-dresdner-philharmonie": {
                        "gnd": null,
                        "viaf": null
                    }
                }
            }
        ],
        "schema:performer": [],
        "schema:workPerformed": [
            {
                "@id": {
                    "https://performance.musiconn.de/work/sinfonien-kv-550-g-moll-mozart-wolfgang-amadeus": {
                        "gnd": "https://d-nb.info/gnd/300111150",
                        "viaf": "https://viaf.org/viaf/193655042"
                    }
                },
                "schema:author": [
                    {
                        "@type": "schema:Person",
                        "@id": {
                            "https://performance.musiconn.de/person/mozart-wolfgang-amadeus-1756-1791": {
                                "gnd": "https://d-nb.info/gnd/118584596",
                                "viaf": "https://viaf.org/viaf/32197206"
                            }
                        }
                    }
                ]
            },
            {
                "@id": {
                    "https://performance.musiconn.de/work/sinfonien-kv-543-es-dur-mozart-wolfgang-amadeus": {
                        "gnd": "https://d-nb.info/gnd/300111134",
                        "viaf": "https://viaf.org/viaf/208684293"
                    }
                },
                "schema:author": [
                    {
                        "@type": "schema:Person",
                        "@id": {
                            "https://performance.musiconn.de/person/mozart-wolfgang-amadeus-1756-1791": {
                                "gnd": "https://d-nb.info/gnd/118584596",
                                "viaf": "https://viaf.org/viaf/32197206"
                            }
                        }
                    }
                ]
            },
            {
                "@id": {
                    "https://performance.musiconn.de/work/sinfonien-kv-551-mozart-wolfgang-amadeus": {
                        "gnd": "https://d-nb.info/gnd/300111169",
                        "viaf": "https://viaf.org/viaf/182681837"
                    }
                },
                "schema:author": [
                    {
                        "@type": "schema:Person",
                        "@id": {
                            "https://performance.musiconn.de/person/mozart-wolfgang-amadeus-1756-1791": {
                                "gnd": "https://d-nb.info/gnd/118584596",
                                "viaf": "https://viaf.org/viaf/32197206"
                            }
                        }
                    }
                ]
            }
        ]
    }
}