{
    "@context": {
        "schema": "http://schema.org/"
    },
    "@id": "https://nfdi4culture.de/id/E4255",
    "schema:event": {
        "@id": "https://performance.musiconn.de/event/grosses-sonderkonzert-opernabend-faunpalast-dresden-1926-01-21-20-00",
        "schema:name": "Gro\u00dfes Sonderkonzert: Opernabend, Faunpalast (Dresden), 21.1.1926, 20:00",
        "schema:location": {
            "https://performance.musiconn.de/location/faunpalast-dresden": {
                "gnd": null,
                "viaf": null
            }
        },
        "schema:temporalCoverage": {
            "@type": "schema:DateTime",
            "@value": "1926-01-21T20:00:00/1926-01-21T20:00:00"
        },
        "schema:alternateName": [
            {
                "@value": "Gro\u00dfes Sonderkonzert: Opernabend"
            }
        ],
        "schema:superEvent": [
            {
                "@type": "schema:Event",
                "@id": {
                    "https://performance.musiconn.de/series/dresdner-philharmonie-spielzeit-1925-1926": {
                        "gnd": null,
                        "viaf": null
                    }
                }
            }
        ],
        "schema:recordedIn": [
            {
                "@id": {
                    "https://performance.musiconn.de/source/konzertarchiv-der-dresdner-philharmonie": {
                        "gnd": null,
                        "viaf": null
                    }
                }
            }
        ],
        "schema:performer": [],
        "schema:workPerformed": [
            {
                "@id": {
                    "https://performance.musiconn.de/work/oberon-ouvertuere-weber-carl-maria-von": {
                        "gnd": "https://d-nb.info/gnd/300171781",
                        "viaf": "https://viaf.org/viaf/309560042"
                    }
                },
                "schema:author": [
                    {
                        "@type": "schema:Person",
                        "@id": {
                            "https://performance.musiconn.de/person/weber-carl-maria-von-1786-1826": {
                                "gnd": "https://d-nb.info/gnd/118629662",
                                "viaf": "https://viaf.org/viaf/14959938"
                            }
                        }
                    }
                ]
            },
            {
                "@id": {
                    "https://performance.musiconn.de/work/fantasie-ueber-la-boheme-puccini-giacomo": {
                        "gnd": null,
                        "viaf": null
                    }
                },
                "schema:author": [
                    {
                        "@type": "schema:Person",
                        "@id": {
                            "https://performance.musiconn.de/person/puccini-giacomo-1858-1924": {
                                "gnd": "https://d-nb.info/gnd/118596942",
                                "viaf": "https://viaf.org/viaf/95156473"
                            }
                        }
                    }
                ]
            },
            {
                "@id": {
                    "https://performance.musiconn.de/work/fantasia-sobre-carmen-de-bizet-sarasate-pablo-de": {
                        "gnd": "https://d-nb.info/gnd/300134738",
                        "viaf": "https://viaf.org/viaf/182728507"
                    }
                },
                "schema:author": [
                    {
                        "@type": "schema:Person",
                        "@id": {
                            "https://performance.musiconn.de/person/sarasate-pablo-de-1844-1908": {
                                "gnd": "https://d-nb.info/gnd/116805455",
                                "viaf": "https://viaf.org/viaf/17408844"
                            }
                        }
                    }
                ]
            },
            {
                "@id": {
                    "https://performance.musiconn.de/work/les-contes-dhoffmann-belle-nuit-o-nuit-damour-offenbach-jacques": {
                        "gnd": "https://d-nb.info/gnd/300115369",
                        "viaf": "https://viaf.org/viaf/185487484"
                    }
                },
                "schema:author": [
                    {
                        "@type": "schema:Person",
                        "@id": {
                            "https://performance.musiconn.de/person/offenbach-jacques-1819-1880": {
                                "gnd": "https://d-nb.info/gnd/118589598",
                                "viaf": "https://viaf.org/viaf/10034167"
                            }
                        }
                    }
                ]
            },
            {
                "@id": {
                    "https://performance.musiconn.de/work/der-schleier-der-pierrette-walzer-dohnanyi-emil-von": {
                        "gnd": null,
                        "viaf": null
                    }
                },
                "schema:author": [
                    {
                        "@type": "schema:Person",
                        "@id": {
                            "https://performance.musiconn.de/person/dohnanyi-emil-von": {
                                "gnd": null,
                                "viaf": null
                            }
                        }
                    }
                ]
            },
            {
                "@id": {
                    "https://performance.musiconn.de/work/die-meistersinger-von-nuernberg-vorspiel-wagner-richard": {
                        "gnd": "https://d-nb.info/gnd/300170114",
                        "viaf": "https://viaf.org/viaf/178619765"
                    }
                },
                "schema:author": [
                    {
                        "@type": "schema:Person",
                        "@id": {
                            "https://performance.musiconn.de/person/wagner-richard-1813-1883": {
                                "gnd": "https://d-nb.info/gnd/118594117",
                                "viaf": "https://viaf.org/viaf/29732107"
                            }
                        }
                    }
                ]
            },
            {
                "@id": {
                    "https://performance.musiconn.de/work/der-ring-des-nibelungen-erster-tag-die-walkuere-leb-wohl-du-kuehnes-herrliches-kind-wagner-richard": {
                        "gnd": "https://d-nb.info/gnd/300170556",
                        "viaf": "https://viaf.org/viaf/207915115"
                    }
                },
                "schema:author": [
                    {
                        "@type": "schema:Person",
                        "@id": {
                            "https://performance.musiconn.de/person/wagner-richard-1813-1883": {
                                "gnd": "https://d-nb.info/gnd/118594117",
                                "viaf": "https://viaf.org/viaf/29732107"
                            }
                        }
                    }
                ]
            },
            {
                "@id": {
                    "https://performance.musiconn.de/work/parsifal-karfreitagszauber-wagner-richard": {
                        "gnd": "https://d-nb.info/gnd/30017019X",
                        "viaf": "https://viaf.org/viaf/176597945"
                    }
                },
                "schema:author": [
                    {
                        "@type": "schema:Person",
                        "@id": {
                            "https://performance.musiconn.de/person/wagner-richard-1813-1883": {
                                "gnd": "https://d-nb.info/gnd/118594117",
                                "viaf": "https://viaf.org/viaf/29732107"
                            }
                        }
                    }
                ]
            },
            {
                "@id": {
                    "https://performance.musiconn.de/work/tannhaeuser-und-der-saengerkrieg-auf-wartburg-ouvertuere-wagner-richard": {
                        "gnd": "https://d-nb.info/gnd/300170475",
                        "viaf": "https://viaf.org/viaf/2916150567609906370005"
                    }
                },
                "schema:author": [
                    {
                        "@type": "schema:Person",
                        "@id": {
                            "https://performance.musiconn.de/person/wagner-richard-1813-1883": {
                                "gnd": "https://d-nb.info/gnd/118594117",
                                "viaf": "https://viaf.org/viaf/29732107"
                            }
                        }
                    }
                ]
            },
            {
                "@id": {
                    "https://performance.musiconn.de/work/die-meistersinger-von-nuernberg-morgenlich-leuchtend-im-rosigen-schein-wagner-richard": {
                        "gnd": "https://d-nb.info/gnd/300170092",
                        "viaf": "https://viaf.org/viaf/211712631"
                    }
                },
                "schema:author": [
                    {
                        "@type": "schema:Person",
                        "@id": {
                            "https://performance.musiconn.de/person/wagner-richard-1813-1883": {
                                "gnd": "https://d-nb.info/gnd/118594117",
                                "viaf": "https://viaf.org/viaf/29732107"
                            }
                        }
                    }
                ]
            }
        ]
    }
}